{
  "description": "项目配置文件。",
  "setting": {
    "urlCheck": false,
    "es6": false,
    "enhance": true,
    "postcss": true,
    "preloadBackgroundData": false,
    "minified": true,
    "newFeature": true,
    "coverView": true,
    "nodeModules": false,
    "autoAudits": false,
    "showShadowRootInWxmlPanel": true,
    "scopeDataCheck": false,
    "uglifyFileName": true,
    "checkInvalidKey": true,
    "checkSiteMap": true,
    "uploadWithSourceMap": true,
    "compileHotReLoad": false,
    "useMultiFrameRuntime": true,
    "babelSetting": {
      "ignore": [],
      "disablePlugins": [],
      "outputPath": ""
    },
    "useIsolateContext": true,
    "useCompilerModule": false,
    "userConfirmedUseCompilerModuleSwitch": false,
    "packNpmManually": false,
    "packNpmRelationList": []
  },
  "miniprogramRoot": "dist/wx/",
  "compileType": "miniprogram",
  "appid": "wxe2f640d4c7bf7173",
  "projectname": "tumeng",
  "simulatorType": "wechat",
  "simulatorPluginLibVersion": {},
  "condition": {
    "search": {
      "current": -1,
      "list": []
    },
    "conversation": {
      "current": -1,
      "list": []
    },
    "game": {
      "currentL": -1,
      "list": []
    },
    "miniprogram": {
      "current": -1,
      "list": []
    }
  }
}